{
"type": "FeatureCollection",
"name": "TitikSungai",
"crs": { "type": "name", "properties": { "name": "urn:ogc:def:crs:OGC:1.3:CRS84" } },
"features": [
{ "type": "Feature", "properties": { "Id": 0, "Sungai": "Sungai Sibam" }, "geometry": { "type": "Point", "coordinates": [ 101.374760554995063, 0.553914744001297 ] } },
{ "type": "Feature", "properties": { "Id": 0, "Sungai": "Sungai Air Hitam" }, "geometry": { "type": "Point", "coordinates": [ 101.395941083994259, 0.548241490000088 ] } },
{ "type": "Feature", "properties": { "Id": 0, "Sungai": "Sungai Umban" }, "geometry": { "type": "Point", "coordinates": [ 101.406323563994093, 0.550673449000048 ] } },
{ "type": "Feature", "properties": { "Id": 0, "Sungai": "Sungai Senapelan 2" }, "geometry": { "type": "Point", "coordinates": [ 101.429586866057647, 0.544806264253558 ] } },
{ "type": "Feature", "properties": { "Id": 0, "Sungai": "Sungai Senapelan 1" }, "geometry": { "type": "Point", "coordinates": [ 101.437489526047173, 0.540945208437725 ] } },
{ "type": "Feature", "properties": { "Id": 0, "Sungai": "Sungai Sago" }, "geometry": { "type": "Point", "coordinates": [ 101.445060544993311, 0.53926721600007 ] } },
{ "type": "Feature", "properties": { "Id": 0, "Sungai": "Sungai Limau" }, "geometry": { "type": "Point", "coordinates": [ 101.447856916993345, 0.538823543000042 ] } },
{ "type": "Feature", "properties": { "Id": 0, "Sungai": "Sungai Meranti Pandak" }, "geometry": { "type": "Point", "coordinates": [ 101.446425590993243, 0.551912729 ] } },
{ "type": "Feature", "properties": { "Id": 0, "Sungai": "Sungai Rumbai" }, "geometry": { "type": "Point", "coordinates": [ 101.453264647993208, 0.556763622000086 ] } },
{ "type": "Feature", "properties": { "Id": 0, "Sungai": "Sungai Sail" }, "geometry": { "type": "Point", "coordinates": [ 101.468291016992893, 0.545466831000331 ] } },
{ "type": "Feature", "properties": { "Id": 0, "Sungai": "Sungai Limbungan" }, "geometry": { "type": "Point", "coordinates": [ 101.472106106992754, 0.556722740000078 ] } },
{ "type": "Feature", "properties": { "Id": 0, "Sungai": "Sungai Taliju" }, "geometry": { "type": "Point", "coordinates": [ 101.483236132992573, 0.554909402000055 ] } },
{ "type": "Feature", "properties": { "Id": 0, "Sungai": "Sungai Pengambang" }, "geometry": { "type": "Point", "coordinates": [ 101.489299476992386, 0.560514698000032 ] } },
{ "type": "Feature", "properties": { "Id": 0, "Sungai": "Sungai Tenayan" }, "geometry": { "type": "Point", "coordinates": [ 101.505490277992109, 0.560484114000077 ] } },
{ "type": "Feature", "properties": { "Id": 0, "Sungai": "Sungai Okura" }, "geometry": { "type": "Point", "coordinates": [ 101.521642509991736, 0.568355447000052 ] } },
{ "type": "Feature", "properties": { "Id": 0, "Sungai": "Sungai Jepun" }, "geometry": { "type": "Point", "coordinates": [ 101.535328512991384, 0.570364856000043 ] } },
{ "type": "Feature", "properties": { "Id": 0, "Sungai": "Sungai Pembuangan" }, "geometry": { "type": "Point", "coordinates": [ 101.54165487999127, 0.568513306000056 ] } },
{ "type": "Feature", "properties": { "Id": 0, "Sungai": "Sungai Putus" }, "geometry": { "type": "Point", "coordinates": [ 101.548305137991022, 0.570665680000064 ] } },
{ "type": "Feature", "properties": { "Id": 0, "Sungai": "Sungai Ukai" }, "geometry": { "type": "Point", "coordinates": [ 101.549181121990998, 0.574539189000016 ] } },
{ "type": "Feature", "properties": { "Id": 0, "Sungai": "Sungai Pendanaan" }, "geometry": { "type": "Point", "coordinates": [ 101.583592496990093, 0.596654421000011 ] } }
]
}
